{"data":{"allMarkdownRemark":{"edges":[{"node":{"id":"ed24177b-e001-5e80-a00a-336604b787d3","frontmatter":{"title":"Testing event emitters with Jest","path":"/blog/jest-event-emitters","date":"2020-06-04"}}},{"node":{"id":"49ec8a7f-f011-547d-9139-a2011de1de8d","frontmatter":{"title":"Coworking in Chiang Mai","path":"/blog/chiang-mai-cowork","date":"2017-03-16"}}},{"node":{"id":"e27d6c23-72b4-5a76-a170-c7918864e502","frontmatter":{"title":"Quick search (q)","path":"/blog/quicksearch","date":"2016-06-06"}}},{"node":{"id":"1dbdbff5-dd16-541e-8d92-c89caaf8cd50","frontmatter":{"title":"Django querysets","path":"/blog/django-querysets","date":"2016-06-06"}}},{"node":{"id":"2766bad2-2a1f-5c2e-916d-394d9b4eda2f","frontmatter":{"title":"Boomerang","path":"/blog/boomerang","date":"2016-04-29"}}}]}}}